openapi_mcp/__init__.py
openapi_mcp/cli.py
openapi_mcp/http_tools.py
openapi_mcp/server.py
openapi_mcp-0.1.0.dist-info/METADATA
openapi_mcp-0.1.0.dist-info/WHEEL
openapi_mcp-0.1.0.dist-info/entry_points.txt
openapi_mcp-0.1.0.dist-info/licenses/LICENSE
openapi_mcp-0.1.0.dist-info/RECORD
