Metadata-Version: 2.4
Name: openapi-mcp
Version: 0.1.0
Summary: Automatic MCP server generator for OpenAPI applications - converts OpenAPI endpoints to MCP tools for LLM integration
Project-URL: Homepage, https://github.com/tadata-org/openapi-mcp
Project-URL: Documentation, https://github.com/tadata-org/openapi-mcp#readme
Project-URL: Bug Tracker, https://github.com/tadata-org/openapi-mcp/issues
Project-URL: PyPI, https://pypi.org/project/openapi-mcp/
Project-URL: Source Code, https://github.com/tadata-org/openapi-mcp
Project-URL: Changelog, https://github.com/tadata-org/openapi-mcp/blob/main/CHANGELOG.md
Author-email: "Tadata Inc." <itay@tadata.com>
License: MIT License
License-File: LICENSE
Keywords: ai,api,claude,conversion,django,fastapi,flask,llm,mcp,openapi,tools
Classifier: Development Status :: 3 - Alpha
Classifier: Intended Audience :: Developers
Classifier: License :: OSI Approved :: MIT License
Classifier: Programming Language :: Python :: 3
Classifier: Programming Language :: Python :: 3.10
Classifier: Programming Language :: Python :: 3.11
Classifier: Programming Language :: Python :: 3.12
Classifier: Topic :: Internet :: WWW/HTTP
Classifier: Topic :: Software Development :: Libraries :: Python Modules
Requires-Python: >=3.10
Requires-Dist: httpx>=0.24.0
Requires-Dist: inspect-mate>=0.0.2
Requires-Dist: mcp>=1.3.0
Requires-Dist: pydantic-settings>=2.5.2
Requires-Dist: pydantic>=2.0.0
Requires-Dist: requests>=2.25.0
Requires-Dist: rich>=13.0.0
Requires-Dist: tomli>=2.2.1
Requires-Dist: typer>=0.9.0
Requires-Dist: uvicorn>=0.20.0
